kawaiipy/__init__.py
kawaiipy/exceptions.py
kawaiipy/types.py
kawaiipy-0.1.0.dist-info/LICENSE
kawaiipy-0.1.0.dist-info/METADATA
kawaiipy-0.1.0.dist-info/WHEEL
kawaiipy-0.1.0.dist-info/RECORD
