Metadata-Version: 2.1
Name: kawaiipy
Version: 0.1.0
Summary: kawaiipy – async wrapper for Kawaii API
License: MIT
Author: stefanlight
Author-email: 64615032+stefanlight8@users.noreply.github.com
Requires-Python: >=3.10,<3.13
Classifier: License :: OSI Approved :: MIT License
Classifier: Programming Language :: Python :: 3
Classifier: Programming Language :: Python :: 3.10
Classifier: Programming Language :: Python :: 3.11
Classifier: Programming Language :: Python :: 3.12
Requires-Dist: aiohttp (>=3.9.5,<4.0.0)
